topsis_Naman_102303352/__init__.py
topsis_Naman_102303352/topsis.py
topsis_naman_102303352-1.0.2.dist-info/licenses/LICENSE.txt
topsis_naman_102303352-1.0.2.dist-info/METADATA
topsis_naman_102303352-1.0.2.dist-info/WHEEL
topsis_naman_102303352-1.0.2.dist-info/entry_points.txt
topsis_naman_102303352-1.0.2.dist-info/top_level.txt
topsis_naman_102303352-1.0.2.dist-info/RECORD
