Metadata-Version: 2.4
Name: Topsis-Naman-102303352
Version: 1.0.2
Summary: A Python package for TOPSIS multi-criteria decision making.
Author: Naman
Classifier: Programming Language :: Python :: 3
Classifier: License :: OSI Approved :: MIT License
Classifier: Operating System :: OS Independent
License-File: LICENSE.txt
Requires-Dist: pandas
Requires-Dist: numpy
Dynamic: author
Dynamic: classifier
Dynamic: description
Dynamic: description-content-type
Dynamic: license-file
Dynamic: requires-dist
Dynamic: summary
